jaraco/pdf/merge.py
jaraco_pdf-1.0.0.dist-info/METADATA
jaraco_pdf-1.0.0.dist-info/WHEEL
jaraco_pdf-1.0.0.dist-info/RECORD
